package stu.base.cls.struct;

import java.util.HashMap;
import java.util.Map;
class Instruction{
	public String mnemonicName;
	public int paraLen;
	public String toString(){
		return mnemonicName;
	}
}
public class OP {
	public Map<String,Instruction> opmap = new HashMap<String,Instruction>();
	private void m(String k,String v){
		Instruction inst = new Instruction();
		inst.mnemonicName=v;
		inst.paraLen=0;
		opmap.put(k, inst);
	}
	private void m(String k,String v,int paraLen){
		Instruction inst = new Instruction();
		inst.mnemonicName=v;
		inst.paraLen=paraLen;
		opmap.put(k, inst);
	}
	public OP(){
		m("00","nop");
		m("01","aconst_null");
		m("02","iconst_m1");
		m("03","iconst_0");
		m("04","iconst_1");
		m("05","iconst_2");
		m("06","iconst_3");
		m("07","iconst_4");
		m("08","iconst_5");
		m("09","lconst_0");
		m("0a","lconst_1");
		m("0b","fconst_0");
		m("0c","fconst_1");
		m("0d","fconst_2");
		m("0e","dconst_0");
		m("0f","dconst_1");
		m("10","bipush",2);
		m("11","sipush",2);
		m("12","ldc",2);
		m("13","ldc_w",2);
		m("14","ldc2_w",2);
		m("15","iload",2);
		m("16","lload",2);
		m("17","fload",2);
		m("18","dload",2);
		m("19","aload",2);
		m("1a","iload_0");
		m("1b","iload_1");
		m("1c","iload_2");
		m("1d","iload_3");
		m("1e","lload_0");
		m("1f","lload_1");
		m("20","lload_2");
		m("21","lload_3");
		m("22","fload_0");
		m("23","fload_1");
		m("24","fload_2");
		m("25","fload_3");
		m("26","dload_0");
		m("27","dload_1");
		m("28","dload_2");
		m("29","dload_3");
		m("2a","aload_0");
		m("2b","aload_1");
		m("2c","aload_2");
		m("2d","aload_3");
		m("2e","iaload",2);
		m("2f","laload",2);
		m("30","faload",2);
		m("31","daload",2);
		m("32","aaload",2);
		m("33","baload",2);
		m("34","caload",2);
		m("35","saload",2);
		m("36","istore",2);
		m("37","lstore",2);
		m("38","fstore",2);
		m("39","dstore",2);
		m("3a","astore",2);
		m("3b","istore_0");
		m("3c","istore_1");
		m("3d","istore_2");
		m("3e","istore_3");
		m("3f","lstore_0");
		m("40","lstore_1");
		m("41","lstore_2");
		m("42","lstore_3");
		m("43","fstore_0");
		m("44","fstore_1");
		m("45","fstore_2");
		m("46","fstore_3");
		m("47","dstore_0");
		m("48","dstore_1");
		m("49","dstore_2");
		m("4a","dstore_3");
		m("4b","astore_0");
		m("4c","astore_1");
		m("4d","astore_2");
		m("4e","astore_3");
		m("4f","iastore",2);
		m("50","lastore",2);
		m("51","fastore",2);
		m("52","dastore",2);
		m("53","aastore",2);
		m("54","bastore",2);
		m("55","castore",2);
		m("56","sastore",2);
		m("57","pop");
		m("58","pop2");
		m("59","dup");
		m("5a","dup_x1");
		m("5b","dup_x2");
		m("5c","dup2");
		m("5d","dup2_x1");
		m("5e","dup2_x2");
		m("5f","swap");
		m("60","iadd");
		m("61","ladd");
		m("62","fadd");
		m("63","dadd");
		m("64","is");
		m("65","ls");
		m("66","fs");
		m("67","ds");
		m("68","imul");
		m("69","lmul");
		m("6a","fmul");
		m("6b","dmul");
		m("6c","idiv");
		m("6d","ldiv");
		m("6e","fdiv");
		m("6f","ddiv");
		m("70","irem");
		m("71","lrem");
		m("72","frem");
		m("73","drem");
		m("74","ineg");
		m("75","lneg");
		m("76","fneg");
		m("77","dneg");
		m("78","ishl");
		m("79","lshl");
		m("7a","ishr");
		m("7b","lshr");
		m("7c","iushr");
		m("7d","lushr");
		m("7e","iand");
		m("7f","land");
		m("80","ior");
		m("81","lor");
		m("82","ixor");
		m("83","lxor");
		m("84","iinc");
		m("85","i2l");
		m("86","i2f");
		m("87","i2d");
		m("88","l2i");
		m("89","l2f");
		m("8a","l2d");
		m("8b","f2i");
		m("8c","f2l");
		m("8d","f2d");
		m("8e","d2i");
		m("8f","d2l");
		m("90","d2f");
		m("91","i2b");
		m("92","i2c");
		m("93","i2s");
		m("94","lcmp");
		m("95","fcmpl");
		m("96","fcmpg");
		m("97","dcmpl");
		m("98","dcmpg");
		m("99","ifeq");
		m("9a","ifne");
		m("9b","iflt");
		m("9c","ifge");
		m("9d","ifgt");
		m("9e","ifle");
		m("9f","if_icmpeq");
		m("a0","if_icmpne");
		m("a1","if_icmplt");
		m("a2","if_icmpge");
		m("a3","if_icmpgt");
		m("a4","if_icmple");
		m("a5","if_acmpeq");
		m("a6","if_acmpne");
		m("a7","goto");
		m("a8","jsr");
		m("a9","ret");
		m("aa","tableswitch");
		m("ab","lookupswitch");
		m("ac","ireturn");
		m("ad","lreturn");
		m("ae","freturn");
		m("af","dreturn");
		m("b0","areturn");
		m("b1","return");
		m("b2","getstatic",2);
		m("b3","putstatic",2);
		m("b4","getfield",2);
		m("b5","putfield",2);
		m("b6","invokevirt",2);
		m("b7","invokespecial",2);
		m("b8","invokestatic",2);
		m("b9","invokeinterface",2);
		m("ba","--");
		m("bb","new",2);
		m("bc","newarray");
		m("bd","anewarray");
		m("be","arraylength");
		m("bf","athrow");
		m("c0","checkcast");
		m("c1","instanceof");
		m("c2","monitorenter");
		m("c3","monitorexit");
		m("c4","wide");
		m("c5","multianewarray");
		m("c6","ifnull");
		m("c7","ifnonnull");
		m("c8","goto_w");
		m("c9","jsr_w");
	}
}
